MANIFEST.in
Makefile
README
setup.py
test/__init__.py
test/test_aliased.py
test/test_booleans.py
test/test_delete.py
test/test_quoted.py
test/test_scoring.py
tiddlywebplugins/__init__.py
tiddlywebplugins/whoosher.py
tiddlywebplugins.whoosher.egg-info/PKG-INFO
tiddlywebplugins.whoosher.egg-info/SOURCES.txt
tiddlywebplugins.whoosher.egg-info/dependency_links.txt
tiddlywebplugins.whoosher.egg-info/namespace_packages.txt
tiddlywebplugins.whoosher.egg-info/not-zip-safe
tiddlywebplugins.whoosher.egg-info/requires.txt
tiddlywebplugins.whoosher.egg-info/top_level.txt