Metadata-Version: 1.0
Name: tiddlywebplugins.whoosher
Version: 0.9.28
Summary: A TiddlyWeb plugin that provides an indexed search interface using Whoosh.
Home-page: http://pypi.python.org/pypi/tiddlywebplugins.whoosher
Author: Chris Dent
Author-email: cdent@peermore.com
License: UNKNOWN
Platform: Posix; MacOS X; Windows
